visualime/__init__.py
visualime/_models.py
visualime/baylime.py
visualime/explain.py
visualime/feature_selection.py
visualime/lime.py
visualime/metrics.py
visualime/visualize.py
visualime-0.1.0.dist-info/LICENSE
visualime-0.1.0.dist-info/METADATA
visualime-0.1.0.dist-info/WHEEL
visualime-0.1.0.dist-info/top_level.txt
visualime-0.1.0.dist-info/RECORD
