Metadata-Version: 2.1
Name: visualime
Version: 0.1.0
Summary: Implementation of LIME focused on producing user-centric local explanations for image classifiers.
Author-email: Kilian Kluge <dev@kluge.ai>, The VisuaLIME developers <xai.demonstrator@gmail.com>
License: Apache 2.0 License
Project-URL: Documentation, https://visualime.readthedocs.io/
Project-URL: Repository, https://github.com/xai-demonstrator/visualime
Project-URL: Bug Tracker, https://github.com/xai-demonstrator/visualime/issues
Classifier: Development Status :: 4 - Beta
Classifier: Programming Language :: Python :: 3
Classifier: License :: OSI Approved :: Apache Software License
Classifier: Operating System :: OS Independent
Requires-Python: >=3.8
License-File: LICENSE
Requires-Dist: numpy (>=1.8.0)
Requires-Dist: Pillow (>=8.0.0)
Requires-Dist: scikit-image (>=0.12)
Requires-Dist: scikit-learn (>=0.24)
